LICENSE
README.md
setup.cfg
setup.py
instagram_dlpy.egg-info/PKG-INFO
instagram_dlpy.egg-info/SOURCES.txt
instagram_dlpy.egg-info/dependency_links.txt
instagram_dlpy.egg-info/requires.txt
instagram_dlpy.egg-info/top_level.txt
instagramdl/__init__.py
instagramdl/api.py
instagramdl/models.py
instagramdl/parser.py
tests/test_urls.py