Metadata-Version: 2.1
Name: instagram-dlpy
Version: 1.1.0
Summary: A python package to download Instagram posts by URL without needing to login
Home-page: https://github.com/Fluxticks/InstagramDL
Download-URL: https://github.com/Fluxticks/InstagramDL/archive/v1.1.0.tar.gz
Author: Fluxticks
Keywords: instagram,api
Classifier: Development Status :: 5 - Production/Stable
Classifier: Intended Audience :: Developers
Classifier: License :: OSI Approved :: GNU General Public License v3 (GPLv3)
Classifier: Programming Language :: Python :: 3.8
Classifier: Programming Language :: Python :: 3.9
Classifier: Programming Language :: Python :: 3.10
License-File: LICENSE
Requires-Dist: requests
